crypto2csv/__init__.py
crypto2csv/main.py
crypto2csv/utils/__init__.py
crypto2csv/utils/api_call.py
crypto2csv/utils/detailed_data.py
crypto2csv/utils/get_dates.py
crypto2csv/utils/historical_data.py
crypto2csv/utils/process.py
crypto2csv-0.1.1.dist-info/LICENSE
crypto2csv-0.1.1.dist-info/METADATA
crypto2csv-0.1.1.dist-info/WHEEL
crypto2csv-0.1.1.dist-info/entry_points.txt
crypto2csv-0.1.1.dist-info/top_level.txt
crypto2csv-0.1.1.dist-info/RECORD
