Metadata-Version: 2.1
Name: crypto2csv
Version: 0.1.1
Summary: A Package to download and saccess cryptocurrecy data using API.
Home-page: https://github.com/prathamagrawal/crypto2csv
Author: Fearsomejockey
Author-email: prathamagrawal1205@gmail.com
License: Apache License 2.0
Platform: UNKNOWN
License-File: LICENSE
Requires-Dist: numpy
Requires-Dist: pandas
Requires-Dist: requests
